autorino/__init__.py
autorino/api/__init__.py
autorino/api/check_rnx.py
autorino/api/configfile_run.py
autorino/api/convert_rnx.py
autorino/api/download_raw.py
autorino/api/splice_rnx_abs.py
autorino/api/splice_rnx_rel.py
autorino/api/split_rnx.py
autorino/bin/__init__.py
autorino/bin/autorino_cfgfile_check.py
autorino/bin/autorino_cfgfile_run.py
autorino/bin/autorino_check_rnx.py
autorino/bin/autorino_convert_rnx.py
autorino/bin/autorino_splice_rnx_relative.py
autorino/bin/autorino_trimble_filelist.py
autorino/cfgenv/__init__.py
autorino/cfgenv/autorino_env_default.yml
autorino/cfgenv/env_read.py
autorino/cfgfiles/__init__.py
autorino/cfgfiles/cfgfile_read.py
autorino/cfgfiles/cfgfiles_utils.py
autorino/cfglog/__init__.py
autorino/cfglog/cfglog.py
autorino/check/__init__.py
autorino/check/check_cls.py
autorino/check/check_fcts.py
autorino/check/trimble_filelist_html.py
autorino/common/__init__.py
autorino/common/decompress.py
autorino/common/eporng_cls.py
autorino/common/eporng_fcts.py
autorino/common/step_cls.py
autorino/common/step_fcts.py
autorino/common/translate.py
autorino/convert/__init__.py
autorino/convert/cnv_cls.py
autorino/convert/cnv_cmd_build.py
autorino/convert/cnv_cmd_run.py
autorino/convert/cnv_fcts.py
autorino/convert/cnv_regex.py
autorino/download/__init__.py
autorino/download/dwl_cls.py
autorino/download/dwl_fcts.py
autorino/handle/__init__.py
autorino/handle/handle_cls.py
autorino/handle/modify_cls.py
autorino/handle/splice_cls.py
autorino/handle/split_cls.py
autorino-2.4.0.dist-info/licenses/LICENSE
autorino-2.4.0.dist-info/METADATA
autorino-2.4.0.dist-info/WHEEL
autorino-2.4.0.dist-info/entry_points.txt
autorino-2.4.0.dist-info/top_level.txt
autorino-2.4.0.dist-info/RECORD
