Metadata-Version: 2.4
Name: autorino
Version: 2.4.0
Summary: autorino is a tool for Assisted Unloading, Treatment & Organisation of RINex Observations
Author-email: Pierre Sakic <sakic@ipgp.fr>
Maintainer-email: Pierre Sakic <sakic@ipgp.fr>
License-Expression: GPL-3.0-or-later
Project-URL: Homepage, https://github.com/IPGP/autorino
Keywords: geodesy,reference frames,RINEX,data management
Classifier: Development Status :: 3 - Alpha
Classifier: Intended Audience :: Developers
Classifier: Topic :: Software Development :: Build Tools
Classifier: Programming Language :: Python :: 3 :: Only
Requires-Python: >=3.8
License-File: LICENSE
Requires-Dist: geodezyx
Requires-Dist: rinexmod
Requires-Dist: dateparser
Requires-Dist: docker
Requires-Dist: filelock
Requires-Dist: numpy
Requires-Dist: pandas
Requires-Dist: PyYAML
Requires-Dist: python-dateutil
Requires-Dist: termcolor
Requires-Dist: hatanaka
Requires-Dist: requests
Requires-Dist: tqdm
Requires-Dist: bs4
Requires-Dist: beautifulsoup4
Requires-Dist: colorlog
Requires-Dist: tabulate
Requires-Dist: matplotlib
Requires-Dist: jinja2
Requires-Dist: colorama
Requires-Dist: logging-tree
Requires-Dist: mergedeep
Dynamic: license-file
